[{"id":1,"name":"Alice","contacts":[{"type":"email","value":"alice@example.com"},{"type":"phone","value":"+123456789"}],"address":{"street":"123 Main St","city":"New York","geo":{"lat":"40.7128","long":"-74.0060"}},"preferences":{"notifications":{"email":true,"sms":false},"categories":["electronics","books"]}},{"id":2,"name":"Bob","contacts":[{"type":"email","value":"bob@example.com"}],"address":{"street":"456 Elm St","city":"San Francisco","geo":{"lat":"37.7749","long":"-122.4194"}},"preferences":{"notifications":{"email":false,"sms":true},"categories":["fashion","sports"]}}]